{
  "template": "https://github.com/runtimeverification/python-project-template.git",
  "commit": "7a095b4dd0a51916da0a728b8fdd9adf7e469a68",
  "checkout": null,
  "context": {
    "cookiecutter": {
      "project_name": "kevm-pyk",
      "project_slug": "kevm-pyk",
      "package_name": "kevm_pyk",
      "version": "0.1.0",
      "description": "",
      "author_name": "Runtime Verification, Inc.",
      "author_email": "contact@runtimeverification.com",
      "_template": "https://github.com/runtimeverification/python-project-template.git",
      "_commit": "7a095b4dd0a51916da0a728b8fdd9adf7e469a68"
    }
  },
  "directory": null
}
